yt_mcp_server_odoo/__init__.py
yt_mcp_server_odoo/__main__.py
yt_mcp_server_odoo/config.py
yt_mcp_server_odoo/odoo_connection.py
yt_mcp_server_odoo/server.py
yt_mcp_server_odoo-0.1.2.dist-info/METADATA
yt_mcp_server_odoo-0.1.2.dist-info/WHEEL
yt_mcp_server_odoo-0.1.2.dist-info/entry_points.txt
yt_mcp_server_odoo-0.1.2.dist-info/RECORD
