Metadata-Version: 2.4
Name: yt-mcp-server-odoo
Version: 0.1.2
Summary: MCP Server for Odoo - Enable AI assistants to interact with Odoo ERP
Project-URL: Homepage, https://yugmatech.com
Project-URL: Repository, https://github.com/yugmatech/yt-mcp-server-odoo
Project-URL: Documentation, https://apps.odoo.com/apps/modules/19.0/yt_mcp_server
Author-email: YugmaTech <hello@yugmatech.com>
License-Expression: LGPL-3.0
Keywords: ai,claude,cursor,mcp,model-context-protocol,odoo
Classifier: Development Status :: 4 - Beta
Classifier: Intended Audience :: Developers
Classifier: License :: OSI Approved :: GNU Lesser General Public License v3 (LGPLv3)
Classifier: Programming Language :: Python :: 3
Classifier: Programming Language :: Python :: 3.10
Classifier: Programming Language :: Python :: 3.11
Classifier: Programming Language :: Python :: 3.12
Requires-Python: >=3.10
Requires-Dist: httpx>=0.27.0
Requires-Dist: mcp>=1.9.4
Requires-Dist: pydantic-settings>=2.0.0
Requires-Dist: pydantic>=2.0.0
Requires-Dist: python-dotenv>=1.0.0
Provides-Extra: dev
Requires-Dist: black>=23.0.0; extra == 'dev'
Requires-Dist: mypy>=1.0.0; extra == 'dev'
Requires-Dist: pytest-asyncio>=0.21.0; extra == 'dev'
Requires-Dist: pytest-cov>=4.0.0; extra == 'dev'
Requires-Dist: pytest>=7.0.0; extra == 'dev'
Requires-Dist: ruff>=0.1.0; extra == 'dev'
